README.md
setup.py
test/test_wait.py
wait/__init__.py
wait/wait.py
wait_util.egg-info/PKG-INFO
wait_util.egg-info/SOURCES.txt
wait_util.egg-info/dependency_links.txt
wait_util.egg-info/top_level.txt