Metadata-Version: 2.1
Name: wait-util
Version: 1.0.0
Summary: wait function used to wait event happens
Home-page: https://github.com/dvdface/waitutil
Author: Ding Yi
Author-email: dvdface@hotmail.com
License: MIT
Platform: UNKNOWN
Classifier: Programming Language :: Python :: 3
Classifier: License :: OSI Approved :: MIT License
Classifier: Operating System :: OS Independent
Requires-Python: >=3.6
